include_guard_convert.py
include_guard_convert-1.0.2.dist-info/licenses/LICENSE
include_guard_convert-1.0.2.dist-info/METADATA
include_guard_convert-1.0.2.dist-info/WHEEL
include_guard_convert-1.0.2.dist-info/entry_points.txt
include_guard_convert-1.0.2.dist-info/top_level.txt
include_guard_convert-1.0.2.dist-info/RECORD
