Metadata-Version: 2.4
Name: include-guard-convert
Version: 1.0.2
Summary: Converts C/C++ preprocessor include guards from the `#ifndef XY_H`, `#define XY_H` to the `#pragma once` paradigm.
Project-URL: Homepage, https://github.com/marcusmueller/include-guard-convert
Requires-Python: >=3.10
License-File: LICENSE
Dynamic: license-file
